api_eazy/__init__.py
api_eazy/api_eazy.py
api_eazy-0.1.5.dist-info/METADATA
api_eazy-0.1.5.dist-info/WHEEL
api_eazy-0.1.5.dist-info/top_level.txt
api_eazy-0.1.5.dist-info/RECORD
